{"contributors": null, "truncated": false, "text": "I'm at Costco in Burbank, CA https://t.co/BXB1hM6Nac", "is_quote_status": false, "in_reply_to_status_id": null, "id": 587724333247819776, "favorite_count": 0, "source": "<a href=\"http://foursquare.com\" rel=\"nofollow\">Foursquare</a>", "retweeted": false, "coordinates": null, "entities": {"symbols": [], "user_mentions": [], "hashtags": [], "urls": [{"url": "https://t.co/BXB1hM6Nac", "indices": [29, 52], "expanded_url": "https://www.swarmapp.com/c/cdNBr4s1j5t", "display_url": "swarmapp.com/c/cdNBr4s1j5t"}]}, "in_reply_to_screen_name": null, "in_reply_to_user_id": null, "retweet_count": 0, "id_str": "587724333247819776", "favorited": false, "user": {"follow_request_sent": false, "has_extended_profile": false, "profile_use_background_image": true, "default_profile_image": false, "id": 102464379, "profile_background_image_url_https": "https://abs.twimg.com/images/themes/theme1/bg.png", "verified": false, "profile_text_color": "333333", "profile_image_url_https": "https://pbs.twimg.com/profile_images/498287572179636224/gXk3JiVq_normal.jpeg", "profile_sidebar_fill_color": "DDEEF6", "entities": {"url": {"urls": [{"url": "http://t.co/xUg4atS0by", "indices": [0, 22], "expanded_url": "http://born2lbfat.com", "display_url": "born2lbfat.com"}]}, "description": {"urls": []}}, "followers_count": 1292, "profile_sidebar_border_color": "C0DEED", "id_str": "102464379", "profile_background_color": "C0DEED", "listed_count": 86, "is_translation_enabled": false, "utc_offset": -10800, "statuses_count": 5532, "description": "Fat describes me, it does not define me. Lipedema, Lymphedema, & WLS patient. Patient Advocate. MS Health Law, 2015 @TEDxNSU Speaker", "friends_count": 1268, "location": "Ohio", "profile_link_color": "0084B4", "profile_image_url": "http://pbs.twimg.com/profile_images/498287572179636224/gXk3JiVq_normal.jpeg", "following": false, "geo_enabled": false, "profile_banner_url": "https://pbs.twimg.com/profile_banners/102464379/1384434541", "profile_background_image_url": "http://abs.twimg.com/images/themes/theme1/bg.png", "screen_name": "Born2lbFat", "lang": "en", "profile_background_tile": false, "favourites_count": 4649, "name": "Sarah Bramblette", "notifications": false, "url": "http://t.co/xUg4atS0by", "created_at": "Wed Jan 06 20:01:56 +0000 2010", "contributors_enabled": false, "time_zone": "Atlantic Time (Canada)", "protected": false, "default_profile": true, "is_translator": false}, "geo": null, "in_reply_to_user_id_str": null, "possibly_sensitive": false, "possibly_sensitive_appealable": false, "lang": "en", "created_at": "Mon Apr 13 21:09:35 +0000 2015", "in_reply_to_status_id_str": null, "place": null}